.gitignore
LICENSE
README.txt
lw12.py
setup.py
test.py
lw12.egg-info/PKG-INFO
lw12.egg-info/SOURCES.txt
lw12.egg-info/dependency_links.txt
lw12.egg-info/top_level.txt