Metadata-Version: 1.2
Name: lw12
Version: 0.9.2
Summary: Library to control the Lagute LW-12 WiFi LED controller.
Home-page: https://github.com/jaypikay/python-lw12
Author: Julian Knauer
Author-email: jpk+lw12dev@goatpr0n.de
License: MIT
Project-URL: Issue Tracker, https://github.com/jaypikay/python-lw12/issues
Project-URL: Source, https://github.com/jaypikay/python-lw12
Keywords: smarthome homeautomation lw12 lagute led light development
Platform: UNKNOWN
Classifier: Development Status :: 4 - Beta
Classifier: Intended Audience :: Developers
Classifier: Topic :: Home Automation
Classifier: Topic :: Internet
Classifier: Topic :: Software Development
Classifier: Topic :: Software Development :: Libraries :: Python Modules
Classifier: License :: OSI Approved :: MIT License
Classifier: Programming Language :: Python :: 3
